awaits/__init__.py
awaits/awaitable.py
awaits/config.py
awaits/errors.py
awaits/py.typed
awaits/room_keeper.py
awaits/shoot.py
awaits/task.py
awaits/threads_pools_room.py
awaits/types.py
awaits/pools/__init__.py
awaits/pools/abstract_pool.py
awaits/pools/threads_pool.py
awaits/protocols/__init__.py
awaits/protocols/queue.py
awaits/units/__init__.py
awaits/units/abstract_unit.py
awaits/units/thread_unit.py
awaits/utils/__init__.py
awaits/utils/end_of_wrappers.py
awaits/utils/get_pool_for_decorator.py
awaits-0.0.14.dist-info/LICENSE
awaits-0.0.14.dist-info/METADATA
awaits-0.0.14.dist-info/WHEEL
awaits-0.0.14.dist-info/top_level.txt
awaits-0.0.14.dist-info/RECORD
