Metadata-Version: 2.1
Name: awaits
Version: 0.0.14
Summary: async + threads + decorators = ?
Author-email: Evgeniy Blinov <zheni-b@yandex.ru>
Project-URL: Source, https://github.com/pomponchik/awaits
Project-URL: Tracker, https://github.com/pomponchik/awaits/issues
Classifier: Operating System :: MacOS :: MacOS X
Classifier: Operating System :: Microsoft :: Windows
Classifier: Operating System :: POSIX
Classifier: Operating System :: POSIX :: Linux
Classifier: Programming Language :: Python
Classifier: Programming Language :: Python :: 3.8
Classifier: Programming Language :: Python :: 3.9
Classifier: Programming Language :: Python :: 3.10
Classifier: Programming Language :: Python :: 3.11
Classifier: Programming Language :: Python :: 3.12
Classifier: Programming Language :: Python :: 3.13
Classifier: Programming Language :: Python :: 3.14
Classifier: License :: OSI Approved :: MIT License
Classifier: Intended Audience :: Developers
Classifier: Topic :: Software Development :: Libraries
Classifier: Framework :: AsyncIO
Requires-Python: >=3.8
License-File: LICENSE
Requires-Dist: skelet>=0.0.2
Requires-Dist: typing-extensions; python_version <= "3.9"
